pynvraw/__init__.py
pynvraw/cuda_api.py
pynvraw/gpu.py
pynvraw/nvapi_api.py
pynvraw/status.py
pynvraw-0.0.7.dist-info/LICENSE
pynvraw-0.0.7.dist-info/METADATA
pynvraw-0.0.7.dist-info/WHEEL
pynvraw-0.0.7.dist-info/top_level.txt
pynvraw-0.0.7.dist-info/RECORD
