Metadata-Version: 2.1
Name: pynvraw
Version: 0.0.7
Summary: Pure-Python wrapper for obscure nvapi
Home-page: https://github.com/JustAMan/pynvraw
Author: Vasily
Author-email: just.one.man@yandex.ru
License: UNKNOWN
Project-URL: Bug Tracker, https://github.com/pypa/sampleproject/issues
Platform: UNKNOWN
Classifier: Programming Language :: Python :: 3
Classifier: License :: OSI Approved :: MIT License
Classifier: Operating System :: Microsoft :: Windows
Requires-Python: >=3.6
License-File: LICENSE
